dtree/__init__.py
dtree/calculators.py
dtree/core.py
dtree/formatters.py
dtree/models.py
dtrees_analyzer-0.1.4.dist-info/licenses/LICENSE
dtrees_analyzer-0.1.4.dist-info/METADATA
dtrees_analyzer-0.1.4.dist-info/WHEEL
dtrees_analyzer-0.1.4.dist-info/top_level.txt
dtrees_analyzer-0.1.4.dist-info/RECORD
