Metadata-Version: 2.4
Name: dtrees-analyzer
Version: 0.1.4
Summary: A Python package for creating, analyzing, and visualizing decision trees with expected value calculations
Author-email: Alejandro Daniel Attento <alejandro@thebyte.guru>
Maintainer-email: Alejandro Daniel Attento <alejandro@thebyte.guru>
License-Expression: MIT
Project-URL: Homepage, https://github.com/AlejandroAttento/DTrees
Project-URL: Repository, https://github.com/AlejandroAttento/DTrees
Project-URL: Issues, https://github.com/AlejandroAttento/DTrees/issues
Keywords: decision-tree,optimization,visualization,mermaid
Classifier: Development Status :: 3 - Alpha
Classifier: Intended Audience :: Developers
Classifier: Intended Audience :: Science/Research
Classifier: Operating System :: OS Independent
Classifier: Programming Language :: Python :: 3.10
Classifier: Programming Language :: Python :: 3.11
Classifier: Programming Language :: Python :: 3.12
Classifier: Topic :: Scientific/Engineering :: Mathematics
Classifier: Topic :: Software Development :: Libraries :: Python Modules
Requires-Python: >=3.10
License-File: LICENSE
Requires-Dist: numpy>=1.20.0
Requires-Dist: mermaid-py>=0.8.0
Requires-Dist: mermaid-cli>=0.1.0
Provides-Extra: dev
Requires-Dist: pytest>=6.0; extra == "dev"
Requires-Dist: black>=21.0; extra == "dev"
Requires-Dist: flake8>=3.8; extra == "dev"
Dynamic: license-file
